nonfig/__init__.py
nonfig/constants.py
nonfig/sdk.py
nonfig/test.py
nonfig_sdk-0.0.3.dist-info/LICENSE
nonfig_sdk-0.0.3.dist-info/METADATA
nonfig_sdk-0.0.3.dist-info/WHEEL
nonfig_sdk-0.0.3.dist-info/top_level.txt
nonfig_sdk-0.0.3.dist-info/RECORD
