Metadata-Version: 2.1
Name: nonfig-sdk
Version: 0.0.3
Summary: UNKNOWN
Home-page: https://github.com/nonfig/python-sdk
Author: Nonfig
Author-email: admin@nonfig.com
License: UNKNOWN
Platform: UNKNOWN
Classifier: Programming Language :: Python :: 3
Classifier: License :: OSI Approved :: MIT License
Classifier: Operating System :: OS Independent
Requires-Python: >=3.6
